volumentations/__init__.py
volumentations/__version__.py
volumentations/random_utils.py
volumentations/augmentations/__init__.py
volumentations/augmentations/functional.py
volumentations/augmentations/functionals.py
volumentations/augmentations/transforms.py
volumentations/core/__init__.py
volumentations/core/composition.py
volumentations/core/transforms_interface.py
volumentations_3D-1.0.4.dist-info/LICENSE
volumentations_3D-1.0.4.dist-info/METADATA
volumentations_3D-1.0.4.dist-info/WHEEL
volumentations_3D-1.0.4.dist-info/top_level.txt
volumentations_3D-1.0.4.dist-info/RECORD
